[{"interaction":"StepBack","tick":"1","pairInteractionTick":"1 - StepBack","sprite2":"wall","sprite1":"butterfly"},{"interaction":"StepBack","tick":"2","pairInteractionTick":"2 - StepBack","sprite2":"wall","sprite1":"butterfly"},{"interaction":"StepBack","tick":"2","pairInteractionTick":"2 - StepBack","sprite2":"wall","sprite1":"butterfly"},{"interaction":"StepBack","tick":"3","pairInteractionTick":"3 - StepBack","sprite2":"wall","sprite1":"butterfly"},{"interaction":"StepBack","tick":"4","pairInteractionTick":"4 - StepBack","sprite2":"wall","sprite1":"butterfly"},{"interaction":"StepBack","tick":"4","pairInteractionTick":"4 - StepBack","sprite2":"wall","sprite1":"butterfly"},{"interaction":"KillSprite","tick":"4","pairInteractionTick":"4 - KillSprite","sprite2":"avatar","sprite1":"butterfly"},{"interaction":"StepBack","tick":"5","pairInteractionTick":"5 - StepBack","sprite2":"wall","sprite1":"butterfly"},{"interaction":"StepBack","tick":"6","pairInteractionTick":"6 - StepBack","sprite2":"wall","sprite1":"butterfly"},{"interaction":"StepBack","tick":"10","pairInteractionTick":"10 - StepBack","sprite2":"wall","sprite1":"butterfly"},{"interaction":"StepBack","tick":"10","pairInteractionTick":"10 - StepBack","sprite2":"wall","sprite1":"butterfly"},{"interaction":"StepBack","tick":"11","pairInteractionTick":"11 - StepBack","sprite2":"wall","sprite1":"butterfly"},{"interaction":"StepBack","tick":"11","pairInteractionTick":"11 - StepBack","sprite2":"wall","sprite1":"butterfly"},{"interaction":"StepBack","tick":"11","pairInteractionTick":"11 - StepBack","sprite2":"wall","sprite1":"butterfly"},{"interaction":"StepBack","tick":"12","pairInteractionTick":"12 - StepBack","sprite2":"wall","sprite1":"butterfly"},{"interaction":"StepBack","tick":"12","pairInteractionTick":"12 - StepBack","sprite2":"wall","sprite1":"butterfly"},{"interaction":"StepBack","tick":"12","pairInteractionTick":"12 - StepBack","sprite2":"wall","sprite1":"butterfly"},{"interaction":"StepBack","tick":"13","pairInteractionTick":"13 - StepBack","sprite2":"wall","sprite1":"butterfly"},{"interaction":"StepBack","tick":"14","pairInteractionTick":"14 - StepBack","sprite2":"wall","sprite1":"butterfly"},{"interaction":"StepBack","tick":"14","pairInteractionTick":"14 - StepBack","sprite2":"wall","sprite1":"butterfly"},{"interaction":"StepBack","tick":"15","pairInteractionTick":"15 - StepBack","sprite2":"wall","sprite1":"butterfly"},{"interaction":"StepBack","tick":"16","pairInteractionTick":"16 - StepBack","sprite2":"wall","sprite1":"butterfly"},{"interaction":"CloneSprite","tick":"16","pairInteractionTick":"16 - CloneSprite","sprite2":"cocoon","sprite1":"butterfly"},{"interaction":"CloneSprite","tick":"16","pairInteractionTick":"16 - CloneSprite","sprite2":"cocoon","sprite1":"butterfly"},{"interaction":"KillSprite","tick":"16","pairInteractionTick":"16 - KillSprite","sprite2":"butterfly","sprite1":"cocoon"},{"interaction":"KillSprite","tick":"16","pairInteractionTick":"16 - KillSprite","sprite2":"butterfly","sprite1":"cocoon"},{"interaction":"KillSprite","tick":"17","pairInteractionTick":"17 - KillSprite","sprite2":"avatar","sprite1":"butterfly"},{"interaction":"CloneSprite","tick":"17","pairInteractionTick":"17 - CloneSprite","sprite2":"cocoon","sprite1":"butterfly"},{"interaction":"KillSprite","tick":"17","pairInteractionTick":"17 - KillSprite","sprite2":"butterfly","sprite1":"cocoon"},{"interaction":"StepBack","tick":"18","pairInteractionTick":"18 - StepBack","sprite2":"wall","sprite1":"butterfly"},{"interaction":"StepBack","tick":"18","pairInteractionTick":"18 - StepBack","sprite2":"wall","sprite1":"butterfly"},{"interaction":"StepBack","tick":"18","pairInteractionTick":"18 - StepBack","sprite2":"wall","sprite1":"butterfly"},{"interaction":"StepBack","tick":"19","pairInteractionTick":"19 - StepBack","sprite2":"wall","sprite1":"butterfly"},{"interaction":"StepBack","tick":"19","pairInteractionTick":"19 - StepBack","sprite2":"wall","sprite1":"butterfly"},{"interaction":"StepBack","tick":"20","pairInteractionTick":"20 - StepBack","sprite2":"wall","sprite1":"avatar"},{"interaction":"StepBack","tick":"20","pairInteractionTick":"20 - StepBack","sprite2":"wall","sprite1":"butterfly"},{"interaction":"StepBack","tick":"20","pairInteractionTick":"20 - StepBack","sprite2":"wall","sprite1":"butterfly"},{"interaction":"StepBack","tick":"21","pairInteractionTick":"21 - StepBack","sprite2":"wall","sprite1":"butterfly"},{"interaction":"StepBack","tick":"21","pairInteractionTick":"21 - StepBack","sprite2":"wall","sprite1":"butterfly"},{"interaction":"StepBack","tick":"22","pairInteractionTick":"22 - StepBack","sprite2":"wall","sprite1":"butterfly"},{"interaction":"StepBack","tick":"22","pairInteractionTick":"22 - StepBack","sprite2":"wall","sprite1":"butterfly"},{"interaction":"StepBack","tick":"23","pairInteractionTick":"23 - StepBack","sprite2":"wall","sprite1":"avatar"},{"interaction":"StepBack","tick":"23","pairInteractionTick":"23 - StepBack","sprite2":"wall","sprite1":"butterfly"},{"interaction":"StepBack","tick":"24","pairInteractionTick":"24 - StepBack","sprite2":"wall","sprite1":"butterfly"},{"interaction":"StepBack","tick":"25","pairInteractionTick":"25 - StepBack","sprite2":"wall","sprite1":"avatar"},{"interaction":"StepBack","tick":"25","pairInteractionTick":"25 - StepBack","sprite2":"wall","sprite1":"butterfly"},{"interaction":"CloneSprite","tick":"25","pairInteractionTick":"25 - CloneSprite","sprite2":"cocoon","sprite1":"butterfly"},{"interaction":"KillSprite","tick":"25","pairInteractionTick":"25 - KillSprite","sprite2":"butterfly","sprite1":"cocoon"},{"interaction":"StepBack","tick":"26","pairInteractionTick":"26 - StepBack","sprite2":"wall","sprite1":"butterfly"},{"interaction":"StepBack","tick":"26","pairInteractionTick":"26 - StepBack","sprite2":"wall","sprite1":"butterfly"},{"interaction":"StepBack","tick":"27","pairInteractionTick":"27 - StepBack","sprite2":"wall","sprite1":"butterfly"},{"interaction":"StepBack","tick":"28","pairInteractionTick":"28 - StepBack","sprite2":"wall","sprite1":"butterfly"},{"interaction":"StepBack","tick":"28","pairInteractionTick":"28 - StepBack","sprite2":"wall","sprite1":"butterfly"},{"interaction":"StepBack","tick":"29","pairInteractionTick":"29 - StepBack","sprite2":"wall","sprite1":"butterfly"},{"interaction":"KillSprite","tick":"29","pairInteractionTick":"29 - KillSprite","sprite2":"avatar","sprite1":"butterfly"},{"interaction":"StepBack","tick":"30","pairInteractionTick":"30 - StepBack","sprite2":"wall","sprite1":"butterfly"},{"interaction":"StepBack","tick":"33","pairInteractionTick":"33 - StepBack","sprite2":"wall","sprite1":"butterfly"},{"interaction":"StepBack","tick":"34","pairInteractionTick":"34 - StepBack","sprite2":"wall","sprite1":"butterfly"},{"interaction":"KillSprite","tick":"36","pairInteractionTick":"36 - KillSprite","sprite2":"avatar","sprite1":"butterfly"},{"interaction":"KillSprite","tick":"38","pairInteractionTick":"38 - KillSprite","sprite2":"avatar","sprite1":"butterfly"},{"interaction":"StepBack","tick":"39","pairInteractionTick":"39 - StepBack","sprite2":"wall","sprite1":"butterfly"},{"interaction":"StepBack","tick":"40","pairInteractionTick":"40 - StepBack","sprite2":"wall","sprite1":"butterfly"},{"interaction":"StepBack","tick":"41","pairInteractionTick":"41 - StepBack","sprite2":"wall","sprite1":"butterfly"},{"interaction":"StepBack","tick":"41","pairInteractionTick":"41 - StepBack","sprite2":"wall","sprite1":"butterfly"},{"interaction":"StepBack","tick":"42","pairInteractionTick":"42 - StepBack","sprite2":"wall","sprite1":"butterfly"},{"interaction":"StepBack","tick":"42","pairInteractionTick":"42 - StepBack","sprite2":"wall","sprite1":"butterfly"},{"interaction":"StepBack","tick":"44","pairInteractionTick":"44 - StepBack","sprite2":"wall","sprite1":"butterfly"},{"interaction":"StepBack","tick":"45","pairInteractionTick":"45 - StepBack","sprite2":"wall","sprite1":"butterfly"},{"interaction":"StepBack","tick":"46","pairInteractionTick":"46 - StepBack","sprite2":"wall","sprite1":"butterfly"},{"interaction":"StepBack","tick":"49","pairInteractionTick":"49 - StepBack","sprite2":"wall","sprite1":"butterfly"},{"interaction":"StepBack","tick":"50","pairInteractionTick":"50 - StepBack","sprite2":"wall","sprite1":"butterfly"},{"interaction":"StepBack","tick":"50","pairInteractionTick":"50 - StepBack","sprite2":"wall","sprite1":"butterfly"},{"interaction":"StepBack","tick":"54","pairInteractionTick":"54 - StepBack","sprite2":"wall","sprite1":"butterfly"},{"interaction":"StepBack","tick":"54","pairInteractionTick":"54 - StepBack","sprite2":"wall","sprite1":"butterfly"},{"interaction":"StepBack","tick":"58","pairInteractionTick":"58 - StepBack","sprite2":"wall","sprite1":"butterfly"},{"interaction":"KillSprite","tick":"58","pairInteractionTick":"58 - KillSprite","sprite2":"avatar","sprite1":"butterfly"},{"interaction":"StepBack","tick":"59","pairInteractionTick":"59 - StepBack","sprite2":"wall","sprite1":"butterfly"},{"interaction":"StepBack","tick":"60","pairInteractionTick":"60 - StepBack","sprite2":"wall","sprite1":"butterfly"},{"interaction":"StepBack","tick":"61","pairInteractionTick":"61 - StepBack","sprite2":"wall","sprite1":"avatar"},{"interaction":"StepBack","tick":"61","pairInteractionTick":"61 - StepBack","sprite2":"wall","sprite1":"butterfly"},{"interaction":"StepBack","tick":"62","pairInteractionTick":"62 - StepBack","sprite2":"wall","sprite1":"butterfly"},{"interaction":"StepBack","tick":"64","pairInteractionTick":"64 - StepBack","sprite2":"wall","sprite1":"butterfly"},{"interaction":"CloneSprite","tick":"66","pairInteractionTick":"66 - CloneSprite","sprite2":"cocoon","sprite1":"butterfly"},{"interaction":"KillSprite","tick":"66","pairInteractionTick":"66 - KillSprite","sprite2":"butterfly","sprite1":"cocoon"},{"interaction":"StepBack","tick":"67","pairInteractionTick":"67 - StepBack","sprite2":"wall","sprite1":"butterfly"},{"interaction":"StepBack","tick":"68","pairInteractionTick":"68 - StepBack","sprite2":"wall","sprite1":"butterfly"},{"interaction":"StepBack","tick":"69","pairInteractionTick":"69 - StepBack","sprite2":"wall","sprite1":"butterfly"},{"interaction":"StepBack","tick":"70","pairInteractionTick":"70 - StepBack","sprite2":"wall","sprite1":"butterfly"},{"interaction":"StepBack","tick":"71","pairInteractionTick":"71 - StepBack","sprite2":"wall","sprite1":"butterfly"},{"interaction":"StepBack","tick":"71","pairInteractionTick":"71 - StepBack","sprite2":"wall","sprite1":"butterfly"},{"interaction":"KillSprite","tick":"71","pairInteractionTick":"71 - KillSprite","sprite2":"avatar","sprite1":"butterfly"},{"interaction":"CloneSprite","tick":"71","pairInteractionTick":"71 - CloneSprite","sprite2":"cocoon","sprite1":"butterfly"},{"interaction":"KillSprite","tick":"71","pairInteractionTick":"71 - KillSprite","sprite2":"butterfly","sprite1":"cocoon"},{"interaction":"StepBack","tick":"72","pairInteractionTick":"72 - StepBack","sprite2":"wall","sprite1":"butterfly"},{"interaction":"StepBack","tick":"72","pairInteractionTick":"72 - StepBack","sprite2":"wall","sprite1":"butterfly"},{"interaction":"StepBack","tick":"72","pairInteractionTick":"72 - StepBack","sprite2":"wall","sprite1":"butterfly"},{"interaction":"KillSprite","tick":"72","pairInteractionTick":"72 - KillSprite","sprite2":"avatar","sprite1":"butterfly"},{"interaction":"StepBack","tick":"73","pairInteractionTick":"73 - StepBack","sprite2":"wall","sprite1":"butterfly"},{"interaction":"StepBack","tick":"73","pairInteractionTick":"73 - StepBack","sprite2":"wall","sprite1":"butterfly"},{"interaction":"StepBack","tick":"73","pairInteractionTick":"73 - StepBack","sprite2":"wall","sprite1":"butterfly"},{"interaction":"StepBack","tick":"74","pairInteractionTick":"74 - StepBack","sprite2":"wall","sprite1":"butterfly"},{"interaction":"StepBack","tick":"74","pairInteractionTick":"74 - StepBack","sprite2":"wall","sprite1":"butterfly"},{"interaction":"StepBack","tick":"74","pairInteractionTick":"74 - StepBack","sprite2":"wall","sprite1":"butterfly"},{"interaction":"StepBack","tick":"75","pairInteractionTick":"75 - StepBack","sprite2":"wall","sprite1":"butterfly"},{"interaction":"KillSprite","tick":"75","pairInteractionTick":"75 - KillSprite","sprite2":"avatar","sprite1":"butterfly"},{"interaction":"StepBack","tick":"76","pairInteractionTick":"76 - StepBack","sprite2":"wall","sprite1":"butterfly"},{"interaction":"StepBack","tick":"77","pairInteractionTick":"77 - StepBack","sprite2":"wall","sprite1":"butterfly"},{"interaction":"StepBack","tick":"78","pairInteractionTick":"78 - StepBack","sprite2":"wall","sprite1":"butterfly"},{"interaction":"StepBack","tick":"79","pairInteractionTick":"79 - StepBack","sprite2":"wall","sprite1":"butterfly"},{"interaction":"StepBack","tick":"80","pairInteractionTick":"80 - StepBack","sprite2":"wall","sprite1":"butterfly"},{"interaction":"StepBack","tick":"81","pairInteractionTick":"81 - StepBack","sprite2":"wall","sprite1":"butterfly"},{"interaction":"StepBack","tick":"82","pairInteractionTick":"82 - StepBack","sprite2":"wall","sprite1":"butterfly"},{"interaction":"KillSprite","tick":"84","pairInteractionTick":"84 - KillSprite","sprite2":"avatar","sprite1":"butterfly"},{"interaction":"KillSprite","tick":"86","pairInteractionTick":"86 - KillSprite","sprite2":"avatar","sprite1":"butterfly"},{"interaction":"KillSprite","tick":"105","pairInteractionTick":"105 - KillSprite","sprite2":"avatar","sprite1":"butterfly"}]